Metadata-Version: 2.1
Name: mwwa
Version: 0.0.1
Summary: mwa
Home-page: UNKNOWN
Author: Michel Rooney
Author-email: michelrooney16@gmail.com
License: MIT License
Keywords: mwa
Platform: UNKNOWN
License-File: LICENCE
